README.rst
setup.py
src/benchsuite/__init__.py
src/benchsuite.rest.egg-info/PKG-INFO
src/benchsuite.rest.egg-info/SOURCES.txt
src/benchsuite.rest.egg-info/dependency_links.txt
src/benchsuite.rest.egg-info/namespace_packages.txt
src/benchsuite.rest.egg-info/requires.txt
src/benchsuite.rest.egg-info/top_level.txt
src/benchsuite/rest/__init__.py
src/benchsuite/rest/app.py
src/benchsuite/rest/apiv1/__init__.py
src/benchsuite/rest/apiv1/benchmarks.py
src/benchsuite/rest/apiv1/executions.py
src/benchsuite/rest/apiv1/model.py
src/benchsuite/rest/apiv1/providers.py
src/benchsuite/rest/apiv1/sessions.py
src/scripts/benchsuite-rest