Metadata-Version: 1.1
Name: benchsuite.rest
Version: 2.3.0.0
Summary: An HTTP REST server to interact with the Benchmarking Suite
Home-page: https://github.com/benchmarking-suite/benchsuite-rest
Author: Gabriele Giammatteo
Author-email: gabriele.giammatteo@eng.it
License: Apache
Keywords: benchmarking cloud testing performance
Platform: UNKNOWN
Classifier: Development Status :: 4 - Beta
Classifier: Intended Audience :: Developers
Classifier: Intended Audience :: Information Technology
Classifier: Topic :: System :: Benchmark
Classifier: Topic :: Utilities
Classifier: Topic :: Software Development :: Testing
Classifier: License :: OSI Approved :: Apache Software License
Classifier: Programming Language :: Python :: 3 :: Only
Classifier: Environment :: Console
Classifier: Operating System :: Unix
Classifier: Framework :: Flask
